pysteg.py
pysteg-0.1.1.dist-info/WHEEL
pysteg-0.1.1.dist-info/METADATA
pysteg-0.1.1.dist-info/RECORD
